tokenizador/__init__.py
tokenizador/abbr_helpers.py
tokenizador/main.py
tokenizador/tokenizador.py
tokenizador/data/en
tokenizador/data/pt
tokenizador-1.50.dist-info/entry_points.txt
tokenizador-1.50.dist-info/LICENSE
tokenizador-1.50.dist-info/WHEEL
tokenizador-1.50.dist-info/METADATA
tokenizador-1.50.dist-info/RECORD
