Metadata-Version: 2.1
Name: tokenizador
Version: 1.50
Summary: Text tokenizer done for SPLN 2022/2023
Author-email: jpdiasfernandes <jpdiasfernandes13@gmail.com>
Classifier: License :: OSI Approved :: MIT License
Project-URL: Source, https://github.com/jpdiasfernandes/spln-2223/tree/master/TPC5/project
